<game_object tsid="DDOADR8FT3V22TN" ts="1355112615962" label="Skills" class_tsid="dc" container="PDOADP8FT3V22TI" upd_gs="gs6" load_time="2012-12-09 20:08:01.000">
	<object id="dynamic">
		<object id="skills">
			<int id="animalkinship_1">1336771091</int>
			<int id="ezcooking_1">1336771806</int>
			<int id="mining_1">1337043000</int>
			<int id="mining_2">1337057645</int>
			<int id="meditativearts_1">1337068914</int>
			<int id="meditativearts_2">1337083345</int>
			<int id="teleportation_1">1337125020</int>
			<int id="focused_meditation_1">1337139420</int>
			<int id="bureaucraticarts_1">1337145985</int>
			<int id="tinkering_1">1337147610</int>
			<int id="cheffery_1">1337150195</int>
			<int id="teleportation_2">1337175180</int>
			<int id="animalkinship_2">1337185980</int>
			<int id="animalkinship_3">1337194324</int>
			<int id="soil_appreciation_1">1337212452</int>
			<int id="tinkering_2">1337219700</int>
			<int id="furnituremaking_1">1337266465</int>
			<int id="tinkering_3">1337305800</int>
			<int id="elementhandling_1">1337310060</int>
			<int id="alchemy_1">1337315820</int>
			<int id="refining_1">1337323440</int>
			<int id="smelting_1">1337378820</int>
			<int id="alchemy_2">1337469506</int>
			<int id="engineering_1">1337504485</int>
			<int id="woodworking_1">1337649134</int>
			<int id="furnituremaking_2">1337749467</int>
			<int id="light_green_thumb_1">1337977140</int>
			<int id="mining_3">1338078078</int>
			<int id="metalwork_1">1338511627</int>
			<int id="soil_appreciation_2">1338864000</int>
			<int id="jellisac_hands_1">1338878719</int>
			<int id="mining_4">1338927211</int>
			<int id="teleportation_3">1339004220</int>
			<int id="meditativearts_3">1339029060</int>
			<int id="soil_appreciation_3">1339037040</int>
			<int id="bogspecialization_1">1339045801</int>
			<int id="fuelmaking_1">1339150871</int>
			<int id="gasmogrification_1">1339180681</int>
			<int id="penmanship_1">1339190412</int>
			<int id="teleportation_4">1339430179</int>
			<int id="gardening_1">1339432860</int>
			<int id="gardening_2">1339441989</int>
			<int id="gardening_3">1339477560</int>
			<int id="gardening_4">1339585800</int>
			<int id="intermediateadmixing_1">1339661950</int>
			<int id="botany_1">1339703360</int>
			<int id="gardening_5">1340175660</int>
			<int id="refining_2">1340255247</int>
			<int id="light_green_thumb_2">1340260510</int>
			<int id="light_green_thumb_3">1340291820</int>
			<int id="soil_appreciation_4">1340337724</int>
			<int id="soil_appreciation_5">1340454377</int>
			<int id="animalkinship_4">1340496840</int>
			<int id="animalkinship_5">1340543179</int>
			<int id="animalhusbandry_1">1340585820</int>
			<int id="animalkinship_6">1340686620</int>
			<int id="distilling_1">1340708965</int>
			<int id="foxbrushing_1">1340737326</int>
			<int id="fiber_arts_1">1340757722</int>
			<int id="fiber_arts_2">1340805183</int>
			<int id="crystalography_1">1340839440</int>
			<int id="tinkering_4">1341022624</int>
			<int id="tinkering_5">1341580800</int>
			<int id="fruitchanging_1">1341594019</int>
			<int id="bubbletuning_1">1341598320</int>
			<int id="herdkeeping_1">1341631625</int>
			<int id="spicemilling_1">1341640350</int>
			<int id="blockmaking_1">1341876780</int>
			<int id="grilling_1">1341896068</int>
			<int id="blending_1">1341901949</int>
			<int id="cocktailcrafting_1">1341919453</int>
			<int id="saucery_1">1341959823</int>
			<int id="teleportation_5">1343127730</int>
			<int id="croppery_1">1343167464</int>
			<int id="bureaucraticarts_2">1343241502</int>
			<int id="croppery_2">1343286085</int>
			<int id="croppery_3">1343473862</int>
			<int id="herbalism_1">1343504182</int>
			<int id="tincturing_1">1343634600</int>
			<int id="potionmaking_1">1343839980</int>
			<int id="saucery_2">1343914106</int>
			<int id="potionmaking_2">1344833580</int>
			<int id="remoteherdkeeping_1">1345136751</int>
			<int id="animalkinship_7">1345927500</int>
			<int id="herbalism_2">1346094864</int>
			<int id="eyeballery_1">1346186760</int>
			<int id="ezcooking_2">1346211780</int>
			<int id="cheffery_2">1346259887</int>
			<int id="cheffery_3">1346286180</int>
			<int id="blending_2">1346342120</int>
			<int id="grilling_2">1346425344</int>
			<int id="cocktailcrafting_2">1346572048</int>
			<int id="herbalism_3">1346957365</int>
			<int id="masterchef_1">1347139263</int>
			<int id="nudgery_1">1347409320</int>
			<int id="potionmaking_3">1349957414</int>
			<int id="transcendental_radiation_1">1350307044</int>
			<int id="levitation_1">1350517438</int>
			<int id="piety_1">1352129024</int>
			<int id="transcendental_radiation_2">1352869355</int>
			<int id="martial_imagination_1">1354018851</int>
		</object>
		<object id="queue">
		</object>
		<int id="capacity">46</int>
		<object id="unlearningQueue">
		</object>
	</object>
</game_object>
